beepy_web_radio/api.py
beepy_web_radio/cli.py
beepy_web_radio/main.py
beepy_web_radio/tui.py
beepy_web_radio-3.0.2.dist-info/LICENSE
beepy_web_radio-3.0.2.dist-info/METADATA
beepy_web_radio-3.0.2.dist-info/WHEEL
beepy_web_radio-3.0.2.dist-info/entry_points.txt
beepy_web_radio-3.0.2.dist-info/RECORD
