Metadata-Version: 2.1
Name: beepy_web_radio
Version: 3.0.2
Summary: Beepy app to play web radio
Home-page: https://github.com/conor-f/beepy-web-radio
License: GPLv3
Author: conor-f
Author-email: beepy@randombits.host
Requires-Python: >=3.9,<4.0
Classifier: License :: Other/Proprietary License
Classifier: Programming Language :: Python :: 3
Classifier: Programming Language :: Python :: 3.9
Classifier: Programming Language :: Python :: 3.10
Classifier: Programming Language :: Python :: 3.11
Classifier: Programming Language :: Python :: 3.12
Classifier: Programming Language :: Python :: 3.13
Requires-Dist: psutil (>=6.0.0,<7.0.0)
Requires-Dist: requests (>=2.32.3,<3.0.0)
Requires-Dist: textual (>=0.82.0,<0.83.0)
